{
  "tab1": {
    "TITLOS_PROSKLHSHS": "sdsdssete",
    "KODIKOS_PROSKLHSHS": "zxssdd",
    "AA_PROSKLHSHS": 222,
    "KODIKOS_FOREA_EGKRISHS": "1011269",
    "ID_XEIRISTHS_PRAXHS_USERNAME": "df",
    "DATE_ENARKSHS_ISXYOS": "15/01/2018",
    "KATHESTOS_ENISXYSHS_LIST": []
  },
  "tab2": [
    {
      "EP_PERIGRAFH": "1",
      "TAMEIO": "01",
      "THEMATIKOI_STOXOI": "26",
      "EPENDYTIKES_PROTERAIOTHTES": "637",
      "EIDIKOI_STOXOI": "702"
    }
  ],
  "tab3": [
    {
      "EIDOS_DEIKTH": "1",
      "ONOMASIA_DEIKTH": "11020 && CO02 - Παραγωγικές επενδύσεις: Αριθμός επιχειρήσεων που λαμβάνουν επιχορηγήσεις"
    },
    {
      "EIDOS_DEIKTH": "1",
      "ONOMASIA_DEIKTH": "11050 && CO05 - Παραγωγικές επενδύσεις: Αριθμός νέων επιχειρήσεων που λαμβάνουν στήριξη"
    },
    {
      "EIDOS_DEIKTH": "1",
      "ONOMASIA_DEIKTH": "11080 && CO08 - Παραγωγικές επενδύσεις: Αύξηση της απασχόλησης στις επιχειρήσεις που λαμβάνουν ενίσχυση"
    },
    {
      "EIDOS_DEIKTH": "1",
      "ONOMASIA_DEIKTH": "54212 && T4212 - Ακαθάριστη Προστιθέμενη Αξία (ΑΠΑ) των 9 στρατηγικών τομέων της χώρας"
    }
  ],
  "tab4": {
    "INVITATION_ABOUT": {
      "CCI_KOINO_SXEDIO_DRASHS": "0",
      "XRHMATOD_PAN_FLAG": "0",
      "ENISXYSH_MME": "0",
      "KOIN_KAIN_DIAKR_SYN": "0",
      "MICRODATA": "0"
    },
    "CODED_DATA_FOR_INVITATION": {
      "OPSMorfh_Xrhmatodothshs_ID_LIST": [],
      "OPSEdafikh_Diastash_Typos_ID_LIST": [],
      "OPSEdafikh_Diastash_Mhxanismos_id_LIST": [],
      "OPSDeytereyon_stoxos_EKT_ID_LIST": [],
      "OPSOikonomikh_Drasthriothta_id_LIST": [],
      "ID_GEO_LIST": []
    }
  },
  "tab5": {
    "PEDIA_PAREMVASHS_OBJ": {
      "PEDIA_PAREMVASHS_LIST": [
        {
          "PEDIA_PAREMVASHS": "3102"
        }
      ],
      "DHMOSIA_DAPANH_TOTAL_OBJ": {}
    },
    "INVITATION_TOTAL_AMOUNTS": {}
  },
  "tab6": {
    "ENTASI_ENISXISIS_OBJ": {
      "min": 25000,
      "max": 400000,
      "MAX_ENTASI_ENISXISIS": 5
    },
    "KATHGORIES_DAPANON_OBJ": {
      "groups": [
        {
          "id": "1",
          "ELAXISTO_POSOSTO_EPI_TOY_PROIPOLOGISMOY": 50
        }
      ],
      "KATHGORIES_DAPANON_LIST": [
        {
          "AA": "1",
          "title": "Κτίρια, λοιπές εγκαταστάσεις και Περιβάλλων χώρος",
          "group": "1",
          "KATHGORIA_ENERGEIAS": "1.",
          "ANOTERO_POSOSTO_EPI_TOY_PROIPOLOGISMOY": 80,
          "ENTASI_ENISXISIS": 45,
          "RITRA_EUELIKSIAS": "0"
        },
        {
          "AA": "2.1",
          "title": "Μηχανήματα – Εξοπλισμός- ",
          "group": "1",
          "ENTASI_ENISXISIS": 45,
          "RITRA_EUELIKSIAS": "0"
        },
        {
          "AA": "2.2",
          "title": "Εγκαταστάσεις και Εξοπλισμός Προστασίας Περιβάλλοντος και Εξοικονόμησης ενέργειας και ύδατος",
          "group": "1",
          "ENTASI_ENISXISIS": 45,
          "RITRA_EUELIKSIAS": "0"
        },
        {
          "AA": "3",
          "title": "Πιστοποίηση συστημάτων διασφάλισης ποιότητας,  περιβαλλοντικής διαχείρισης",
          "ANOTERO_POSO": "12000",
          "ENTASI_ENISXISIS": 45,
          "RITRA_EUELIKSIAS": "0"
        },
        {
          "AA": "4",
          "title": "Προβολή – Προώθηση - Συμμετοχή σε Εκθέσεις",
          "ANOTERO_POSO": "15000",
          "ENTASI_ENISXISIS": 45,
          "RITRA_EUELIKSIAS": "0"
        },
        {
          "AA": "5",
          "title": "Δαπάνες τεχνικών μελετών Μηχανικού και υπηρεσιών Φοροτεχνικού και Νομικού Συμβούλου.",
          "ANOTERO_POSO": "40000",
          "ENTASI_ENISXISIS": 45,
          "RITRA_EUELIKSIAS": "0"
        },
        {
          "AA": "6",
          "title": "Λογισμικά και Υπηρεσίες Λογισμικού",
          "ANOTERO_POSO": "10000",
          "ENTASI_ENISXISIS": 45,
          "RITRA_EUELIKSIAS": "0"
        },
        {
          "AA": "7",
          "title": "Μεταφορικά μέσα",
          "ANOTERO_POSO": "25000",
          "ENTASI_ENISXISIS": 45,
          "RITRA_EUELIKSIAS": "0"
        },
        {
          "AA": "8",
          "title": "Σύνταξη και Παρακολούθηση υλοποίησης του Επενδυτικού Σχεδίου",
          "ANOTERO_POSO": "4000",
          "ENTASI_ENISXISIS": 45,
          "RITRA_EUELIKSIAS": "0"
        }
      ]
    }
  },
  "tab7": {
    "attachmentInstruction": "Τα επισυναπτόμενα αρχεία τα οποία αναφέρονται στο παράρτημα Ι του οδηγού του προγράμματος θα πρέπει να είναι σε μη επεξεργάσιμη ηλεκτρονική μορφή αρχείου (πχ αρχείο τύπου pdf). Κάθε επισυναπτόμενο έγγραφο θα πρέπει να έχει χωρητικότητα μέχρι 10 ΜΒ.",
    "attachment": []
  },
  "tab8": {
    "onOff": [],
    "groupOnOff": [],
    "critiria": [],
    "group": []
  },
  "compiled": "{\"GenericCheckpoints_qCategory67_c204\":{\"hidden\":\"1\",\"columns\":[]},\"GenericCheckpoints_qCategory68_c204\":{\"hidden\":\"1\",\"columns\":[]},\"GenericCheckpoints_qCategory69_c204\":{\"hidden\":\"1\",\"columns\":[]},\"GenericCheckpoints_qCategory16_c204\":{\"hidden\":1},\"GenericCheckpoints_qCategory74_c204\":{\"hidden\":1},\"DeMinimisProject_qType1_c204\":{\"columns\":[{\"view\":\"\",\"edit\":\"\",\"name\":\"DeMinimisProjectID\"},{\"view\":\"\",\"edit\":\"\",\"name\":\"DMI_TypeID\"},{\"view\":\"\",\"edit\":\"\",\"name\":\"DMI_ContractorID\"}]},\"DeMinimisProject_qType2_c204\":{\"columns\":[{\"view\":\"\",\"edit\":\"\",\"name\":\"DeMinimisProjectID\"},{\"view\":\"\",\"edit\":\"\",\"name\":\"DMI_TypeID\"},{\"view\":\"\",\"edit\":\"\",\"name\":\"DMI_ContractorID\"}]},\"DeMinimisProject_qType3_c204\":{\"columns\":[{\"view\":\"\",\"edit\":\"\",\"name\":\"DeMinimisProjectID\"},{\"view\":\"\",\"edit\":\"\",\"name\":\"DMI_TypeID\"},{\"view\":\"\",\"edit\":\"\",\"name\":\"DMI_ContractorID\"}]},\"DeMinimisProject_qType4_c204\":{\"columns\":[{\"view\":\"\",\"edit\":\"\",\"name\":\"DeMinimisProjectID\"},{\"view\":\"\",\"edit\":\"\",\"name\":\"DMI_TypeID\"},{\"view\":\"\",\"edit\":\"\",\"name\":\"DMI_ContractorID\"}]},\"ContractorCompaniesShareholders_qMulti_c204\":{\"columns\":[{\"view\":\"\",\"edit\":\"\",\"name\":\"FullName\"},{\"view\":\"\",\"edit\":\"\",\"name\":\"LegalRepSurname\"},{\"view\":\"\",\"edit\":\"\",\"name\":\"LegalRepName\"},{\"view\":\"\",\"edit\":\"\",\"name\":\"LegalRepFatherName\"},{\"view\":\"\",\"edit\":\"\",\"name\":\"LegalRepDocument\"}]},\"ModificationContractContact_qType302_c204\":{\"columns\":[{\"view\":\"\",\"edit\":\"\",\"name\":\"ContractID\"},{\"view\":\"\",\"edit\":\"\",\"name\":\"CI_Municipality_Code\"},{\"view\":\"\",\"edit\":\"\",\"name\":\"CI_ContactInfoType_Code\"},{\"view\":\"\",\"edit\":\"\",\"name\":\"CI_IdentityDoc\"},{\"view\":\"\",\"edit\":\"\",\"name\":\"CI_TIN\"},{\"view\":\"\",\"edit\":\"\",\"name\":\"CI_CountryISO_Code\"},{\"view\":\"\",\"edit\":\"\",\"name\":\"CNT_VAT\"}]},\"RelatedKAD2008Info_qMulti_c204\":{\"hidden\":\"\",\"single\":\"\",\"help-on\":\"1\",\"helptext\":\"Οι επιχειρήσεις της κατηγορίας Β μπορούν να επιλέξουν ως ΚΑΔ επένδυσης έναν τουλάχιστον μόνο από τους επιλέξιμους ΚΑΔ 55 του Παραρτήματος V ή και τους ΚΑΔ 41.20.20.01 ή 41.20.20.02. Η ημερομηνία προσθήκης θα πρέπει να είναι πριν από την προκήρυξη της δράσης (7/11/2017).\",\"edit\":\"1\",\"columns\":[{\"view\":\"\",\"edit\":\"\",\"name\":\"RelatedEntityType\"}]},\"ModificationContractor_qMulti_c204\":{\"single\":\"1\",\"columns\":[{\"name\":\"P_TaxCode\",\"data-hide-when\":\"{{CNT_ActivitiesDescription}} <= 200\"},{\"name\":\"CNT_TaxAuthority\",\"data-hide-when\":\"{{CNT_ActivitiesDescription}} <= 200\"},{\"name\":\"CNT_FoundingYear\",\"data-hide-when\":\"{{CNT_ActivitiesDescription}} <= 200\"},{\"name\":\"CNT_LegalTypeID\",\"data-hide-when\":\"{{CNT_ActivitiesDescription}} <= 200\"},{\"name\":\"P_TaxOffice_Text\",\"data-hide-when\":\"{{CNT_ActivitiesDescription}} <= 200\"},{\"name\":\"CNT_TaxBookTypeID\",\"data-hide-when\":\"{{CNT_ActivitiesDescription}} <= 200\"},{\"name\":\"CNT_AssociationNumber\",\"edit\":\"\",\"view\":\"\"},{\"name\":\"CNT_InStockMarket\",\"edit\":\"\",\"view\":\"\"},{\"name\":\"CNT_ActivitiesDescription\",\"items\":[{\"val\":0,\"lab\":\"Επιχείρηση Κατηγορίας Α’ της Πρόσκλησης (Νέα δραστηριότητα)\"},{\"val\":201,\"lab\":\"Επιχείρηση Κατηγορίας Β’ της Πρόσκλησης (Υφιστάμενη δραστηριότητα)\"}]},{\"name\":\"CNT_SizeIndicator\",\"items\":[{\"val\":\"1\",\"lab\":\"Πολύ Μικρή\"},{\"val\":\"2\",\"lab\":\"Μικρή\"},{\"val\":\"3\",\"lab\":\"Μεσαία\"}]},{\"view\":\"\",\"edit\":\"\",\"name\":\"CNT_TaxBookTypeOnSubmitID\"},{\"view\":\"\",\"edit\":\"\",\"name\":\"CNT_LegalTypeOnSubmitID\"},{\"view\":\"\",\"edit\":\"\",\"name\":\"CNT_TaxBookTypeOnSubmitID\"},{\"view\":\"\",\"edit\":\"\",\"name\":\"CNT_LegalTypeOnSubmitID\"},{\"view\":\"\",\"edit\":\"\",\"name\":\"CNT_AtLeastThreeUses\"},{\"view\":\"\",\"edit\":\"\",\"name\":\"UpdatedCheckPoints\"},{\"view\":\"\",\"edit\":\"\",\"name\":\"CNT_ActivitySectorTypeID\"},{\"view\":\"\",\"edit\":\"\",\"name\":\"CNT_KyklosErgasionN1\"},{\"view\":\"\",\"edit\":\"\",\"name\":\"CNT_KyklosErgasionN2\"},{\"view\":\"\",\"edit\":\"\",\"name\":\"CNT_KyklosErgasionN3\"},{\"view\":\"\",\"edit\":\"\",\"name\":\"CNT_KerdiProForonN1\"},{\"view\":\"\",\"edit\":\"\",\"name\":\"CNT_KerdiProForonN2\"},{\"view\":\"\",\"edit\":\"\",\"name\":\"CNT_IdiaKefalaiaN1\"},{\"view\":\"\",\"edit\":\"\",\"name\":\"CNT_IdiaKefalaiaN2\"},{\"view\":\"\",\"edit\":\"\",\"name\":\"CNT_XenaKefalaiaN1\"},{\"view\":\"\",\"edit\":\"\",\"name\":\"CNT_XenaKefalaiaN2\"},{\"view\":\"\",\"edit\":\"\",\"name\":\"CNT_KerdiE3N1\"},{\"view\":\"\",\"edit\":\"\",\"name\":\"CNT_KerdiE3N2\"},{\"view\":\"\",\"edit\":\"\",\"name\":\"CNT_Agores\"},{\"view\":\"\",\"edit\":\"\",\"name\":\"CNT_Amoives\"},{\"view\":\"\",\"edit\":\"\",\"name\":\"CNT_ResponsibleCourt\"},{\"view\":\"\",\"edit\":\"\",\"name\":\"CNT_ContractorKAD1\"},{\"view\":\"\",\"edit\":\"\",\"name\":\"CNT_ContractorKAD2\"},{\"view\":\"\",\"edit\":\"\",\"name\":\"CNT_ContractorKAD3\"},{\"view\":\"\",\"edit\":\"\",\"name\":\"CNT_ContractorKAD4\"},{\"view\":\"\",\"edit\":\"\",\"name\":\"CNT_FundedActivityRevenuePercentage2\"},{\"view\":\"\",\"edit\":\"\",\"name\":\"CNT_FundedActivityRevenuePercentage3\"},{\"view\":\"\",\"edit\":\"\",\"name\":\"CNT_FundedActivityRevenuePercentage4\"},{\"view\":\"\",\"edit\":\"\",\"name\":\"CI_MobilePhone\"},{\"view\":\"\",\"edit\":\"\",\"name\":\"CNT_CompaniesParticipation\"},{\"view\":\"\",\"edit\":\"\",\"name\":\"CNT_AuditTaxBookTypeID\"},{\"view\":\"\",\"edit\":\"\",\"name\":\"CNT_EstimatedSubmissionDate\"},{\"view\":\"\",\"edit\":\"\",\"name\":\"CNT_CharacterisedAsNewCompany\"},{\"view\":\"\",\"edit\":\"\",\"name\":\"CNT_ProductiveYears\"},{\"view\":\"\",\"edit\":\"\",\"name\":\"CNT_NameAfterChange\"},{\"view\":\"\",\"edit\":\"\",\"name\":\"CNT_CustomDate\"},{\"view\":\"\",\"edit\":\"\",\"name\":\"CNT_IsNewCompanyCreated\"},{\"view\":\"\",\"edit\":\"\",\"name\":\"CNT_OtherLegalType\"},{\"view\":\"\",\"edit\":\"\",\"name\":\"CI_Phone_2\"},{\"view\":\"\",\"edit\":\"\",\"name\":\"CI_Email_2\"},{\"view\":\"\",\"edit\":\"\",\"name\":\"CNT_PeriodWithProfits\"},{\"view\":\"\",\"edit\":\"\",\"name\":\"CNT_PeriodWithProfitsFrom\"},{\"view\":\"\",\"edit\":\"\",\"name\":\"CNT_PeriodWithProfitsTo\"},{\"view\":\"\",\"edit\":\"\",\"name\":\"CI_Address_2\"},{\"view\":\"\",\"edit\":\"\",\"name\":\"CI_PostCode_2\"},{\"view\":\"\",\"edit\":\"\",\"name\":\"CI_Municipality_Code_2\"},{\"view\":\"\",\"edit\":\"\",\"name\":\"CI_Fax_2\"}]},\"ContractorShareholders_qMulti_c204\":{\"helptext\":\"Αν υπάρχουν πολλοί μέτοχοι, να καταχωρηθούν οι τρεις με το μεγαλύτερο ποσοστό.\",\"columns\":[{\"name\":\"CS_ExtraDocument\",\"data-hide-when\":\"{{CS_Type}} == 2\"},{\"name\":\"CS_FirstName\",\"data-hide-when\":\"{{CS_Type}} == 1\"},{\"name\":\"CS_ExtraAfm\",\"data-hide-when\":\"{{CS_Type}} == 1\"},{\"name\":\"CS_YearFounded\",\"data-hide-when\":\"{{CS_Type}} == 1\"},{\"name\":\"CS_RelativeExperienceInfo\",\"edit\":\"1\",\"hidden\":\"\",\"required\":\"1\",\"items\":[{\"val\":\"1\",\"lab\":\"1. Τουριστική επαγγελματική εμπειρία\"},{\"val\":\"2\",\"lab\":\"2. Γενική επαγγελματική εμπειρία\"}]},{\"name\":\"CS_RelativeStudiesInfo\",\"edit\":\"1\",\"required\":\"1\",\"hidden\":\"\"},{\"name\":\"CS_ShareholderPosition\",\"required\":\"1\"},{\"view\":\"\",\"edit\":\"\",\"name\":\"CS_Municipality_Code\"},{\"view\":\"\",\"edit\":\"\",\"name\":\"CS_PercentOwnedAfterInvestment\"},{\"view\":\"\",\"edit\":\"\",\"name\":\"CS_LegalTypeID\"},{\"view\":\"\",\"edit\":\"\",\"name\":\"CS_ActivityText\"},{\"view\":\"\",\"edit\":\"\",\"name\":\"CS_IsAdministrator\"},{\"view\":\"\",\"edit\":\"\",\"name\":\"CS_Occupation\"},{\"view\":\"\",\"edit\":\"\",\"name\":\"CS_IdentityNo\"},{\"view\":\"\",\"edit\":\"\",\"name\":\"CS_CompanyRegistrationNo\"},{\"view\":\"\",\"edit\":\"\",\"name\":\"CS_WebSite\"},{\"view\":\"\",\"edit\":\"\",\"name\":\"CS_Reserved2\"},{\"view\":\"\",\"edit\":\"\",\"name\":\"CS_EmployeesCount\"},{\"view\":\"\",\"edit\":\"\",\"name\":\"CS_LastFiscalYearGrossProfits\"},{\"view\":\"\",\"edit\":\"\",\"name\":\"CS_PassportIndicator\"},{\"view\":\"\",\"edit\":\"\",\"name\":\"CS_CountryOfResidenceDescription\"},{\"view\":\"\",\"edit\":\"\",\"name\":\"CS_RelativeJobTraining\"},{\"view\":\"\",\"edit\":\"\",\"name\":\"CS_ContactResponsiblePhone\"},{\"view\":\"\",\"edit\":\"\",\"name\":\"CS_IsGradeable\"},{\"view\":\"\",\"edit\":\"\",\"name\":\"CS_HasManagmentPosition\"},{\"view\":\"\",\"edit\":\"\",\"name\":\"CS_ManagmentPosition\"},{\"view\":\"\",\"edit\":\"\",\"name\":\"CS_ManagmentPositionOther\"},{\"view\":\"\",\"edit\":\"\",\"name\":\"CS_ExtraSurname\"},{\"view\":\"\",\"edit\":\"\",\"name\":\"CS_ExtraName\"},{\"view\":\"\",\"edit\":\"\",\"name\":\"CS_ExtraFatherName\"},{\"view\":\"\",\"edit\":\"\",\"name\":\"CS_ExtraPosition\"},{\"view\":\"\",\"edit\":\"\",\"name\":\"CS_HasUnemploymentCard\"},{\"view\":\"\",\"edit\":\"\",\"name\":\"CS_NonRelativeExperience\"},{\"view\":\"\",\"edit\":\"\",\"name\":\"CS_NonRelativeExperienceInfo\"},{\"view\":\"\",\"edit\":\"\",\"name\":\"CS_RelativeJobTrainingInfo\"},{\"view\":\"\",\"edit\":\"\",\"name\":\"CS_UnemployProof\"},{\"view\":\"\",\"edit\":\"\",\"name\":\"CS_KritiriaProt\"},{\"view\":\"\",\"edit\":\"\",\"name\":\"CS_ApeiloumeniProof\"},{\"view\":\"\",\"edit\":\"\",\"name\":\"CS_FoundationDate\"},{\"view\":\"\",\"edit\":\"\",\"name\":\"CS_MaritalStatus\"},{\"view\":\"\",\"edit\":\"\",\"name\":\"CS_TaxCountry\"}]},\"GenericCheckpoints_qCategory17_c204\":{\"single\":\"1\",\"columns\":[{\"name\":\"Comments1\",\"label\":\"2015\"},{\"name\":\"Comments4\",\"label\":\"2016\"},{\"name\":\"Comments7\",\"label\":\"2017\",\"edit\":\"\",\"view\":\"\"},{\"name\":\"Comments8\",\"edit\":\"\",\"view\":\"\"},{\"name\":\"Comments9\",\"edit\":\"\",\"view\":\"\"},{\"name\":\"Comments10\",\"edit\":\"\",\"view\":\"\"},{\"name\":\"Comments11\",\"edit\":\"\",\"view\":\"\"},{\"name\":\"Comments12\",\"edit\":\"\",\"view\":\"\"},{\"name\":\"Comments13\",\"edit\":\"\",\"view\":\"\"},{\"view\":\"\",\"edit\":\"\",\"name\":\"GenericCheckpointsID\"},{\"view\":\"\",\"edit\":\"\",\"name\":\"RelatedEntityType\"},{\"view\":\"\",\"edit\":\"\",\"name\":\"CpCode1\"},{\"view\":\"\",\"edit\":\"\",\"name\":\"CpCode2\"},{\"view\":\"\",\"edit\":\"\",\"name\":\"CpCode3\"},{\"view\":\"\",\"edit\":\"\",\"name\":\"CpCode4\"},{\"view\":\"\",\"edit\":\"\",\"name\":\"CpCode5\"},{\"view\":\"\",\"edit\":\"\",\"name\":\"CpCode6\"},{\"view\":\"\",\"edit\":\"\",\"name\":\"CpCode7\"},{\"view\":\"\",\"edit\":\"\",\"name\":\"CpCode8\"},{\"view\":\"\",\"edit\":\"\",\"name\":\"CpCode9\"},{\"view\":\"\",\"edit\":\"\",\"name\":\"CpCode10\"},{\"view\":\"\",\"edit\":\"\",\"name\":\"IntVal1\"},{\"view\":\"\",\"edit\":\"\",\"name\":\"IntVal2\"},{\"view\":\"\",\"edit\":\"\",\"name\":\"IntVal3\"},{\"view\":\"\",\"edit\":\"\",\"name\":\"IntVal4\"},{\"view\":\"\",\"edit\":\"\",\"name\":\"IntVal5\"},{\"view\":\"\",\"edit\":\"\",\"name\":\"IntVal6\"},{\"view\":\"\",\"edit\":\"\",\"name\":\"IntVal7\"},{\"view\":\"\",\"edit\":\"\",\"name\":\"IntVal8\"},{\"view\":\"\",\"edit\":\"\",\"name\":\"IntVal9\"},{\"view\":\"\",\"edit\":\"\",\"name\":\"IntVal10\"},{\"view\":\"\",\"edit\":\"\",\"name\":\"IntVal11\"},{\"view\":\"\",\"edit\":\"\",\"name\":\"IntVal12\"},{\"view\":\"\",\"edit\":\"\",\"name\":\"IntVal13\"},{\"view\":\"\",\"edit\":\"\",\"name\":\"DecVal1\"},{\"view\":\"\",\"edit\":\"\",\"name\":\"DecVal2\"},{\"view\":\"\",\"edit\":\"\",\"name\":\"DecVal3\"},{\"view\":\"\",\"edit\":\"\",\"name\":\"DecVal4\"},{\"view\":\"\",\"edit\":\"\",\"name\":\"DecVal5\"},{\"view\":\"\",\"edit\":\"\",\"name\":\"DecVal6\"},{\"view\":\"\",\"edit\":\"\",\"name\":\"DecVal7\"},{\"view\":\"\",\"edit\":\"\",\"name\":\"DecVal8\"},{\"view\":\"\",\"edit\":\"\",\"name\":\"DecVal9\"},{\"view\":\"\",\"edit\":\"\",\"name\":\"DecVal10\"},{\"view\":\"\",\"edit\":\"\",\"name\":\"DateVal1\"},{\"view\":\"\",\"edit\":\"\",\"name\":\"DateVal2\"},{\"view\":\"\",\"edit\":\"\",\"name\":\"DateVal3\"},{\"view\":\"\",\"edit\":\"\",\"name\":\"DateVal4\"},{\"view\":\"\",\"edit\":\"\",\"name\":\"DateVal5\"},{\"view\":\"\",\"edit\":\"\",\"name\":\"DateVal6\"},{\"view\":\"\",\"edit\":\"\",\"name\":\"DateVal7\"},{\"view\":\"\",\"edit\":\"\",\"name\":\"DateVal8\"},{\"view\":\"\",\"edit\":\"\",\"name\":\"DateVal9\"},{\"view\":\"\",\"edit\":\"\",\"name\":\"DateVal10\"}]},\"GenericCheckpoints_qCategory41_c204\":{\"hiddenColumns\":[\"GenericCheckpointsID\",\"RelatedEntityType\",\"RelatedEntityID\",\"CpCode1\",\"CpCode2\",\"CpCode3\",\"CpCode4\",\"CpCode5\",\"CpCode6\",\"CpCode7\",\"CpCode8\",\"CpCode9\",\"CpCode10\",\"IntVal2\",\"IntVal3\",\"IntVal4\",\"IntVal5\",\"IntVal6\",\"IntVal7\",\"IntVal8\",\"IntVal9\",\"IntVal10\",\"IntVal11\",\"IntVal12\",\"IntVal13\",\"Comments4\",\"Comments5\",\"Comments6\",\"Comments7\",\"Comments8\",\"Comments9\",\"Comments10\",\"Comments11\",\"Comments12\",\"Comments13\",\"DateVal1\",\"DateVal2\",\"DateVal3\",\"DateVal4\",\"DateVal5\",\"DateVal6\",\"DateVal7\",\"DateVal8\",\"DateVal9\",\"DateVal10\",\"DecVal1\",\"DecVal2\",\"DecVal3\",\"DecVal4\",\"DecVal5\",\"DecVal6\",\"DecVal7\",\"DecVal8\",\"DecVal9\",\"DecVal10\"],\"columns\":[{\"edit\":\"1\",\"view\":\"1\",\"name\":\"Comments3\",\"items\":[{\"val\":\"1\",\"lab\":\"Ίδρυση\"},{\"val\":\"2\",\"lab\":\"Εκσυγχρονισμός\"},{\"val\":\"3\",\"lab\":\"Επέκταση\"},{\"val\":\"4\",\"lab\":\"Εκσυγχρονισμός/Επέκταση\"},{\"val\":\"5\",\"lab\":\"Μετεγκατάσταση\"},{\"val\":\"6\",\"lab\":\"Εκπαίδευση\"},{\"val\":\"7\",\"lab\":\"Συνεργασία\"}]}]},\"ModificationContractContact_qType601_c204\":{\"help-on\":\"1\",\"helptext\":\"Όλοι οι τόποι υλοποίησης να ανήκουν στην ίδια περιφέρεια\",\"hiddenColumns\":[\"ContractID\",\"CI_Reserved1\",\"CI_LastName\",\"CI_FirstName\",\"CI_MobilePhone\",\"CI_Phone_1\",\"CI_Fax_1\",\"CI_Email_1\",\"CI_Municipality_Code\",\"CI_TaxCode\",\"CI_AdtOrPassportNo\",\"CI_Comments\",\"CI_AdtOrPassportIndicator\",\"CI_AdtOrPassportCountry\",\"CI_IdentityDoc\",\"CI_TIN\",\"CI_CountryISO_Code\",\"CNT_VAT\"],\"columns\":[]},\"GenericCheckpoints_qCategory3_c204\":{\"hiddenColumns\":[\"GenericCheckpointsID\",\"RelatedEntityType\",\"RelatedEntityID\",\"CpCode1\",\"CpCode2\",\"CpCode3\",\"CpCode4\",\"CpCode5\",\"CpCode6\",\"CpCode7\",\"CpCode8\",\"CpCode9\",\"CpCode10\",\"IntVal5\",\"IntVal9\",\"IntVal10\",\"IntVal11\",\"IntVal12\",\"IntVal13\",\"Comments2\",\"Comments3\",\"Comments4\",\"Comments5\",\"Comments6\",\"Comments7\",\"Comments8\",\"Comments9\",\"Comments10\",\"Comments11\",\"Comments12\",\"Comments13\",\"DateVal1\",\"DateVal2\",\"DateVal3\",\"DateVal4\",\"DateVal5\",\"DateVal6\",\"DateVal7\",\"DateVal8\",\"DateVal9\",\"DateVal10\",\"DecVal1\",\"DecVal2\",\"DecVal3\",\"DecVal4\",\"DecVal5\",\"DecVal6\",\"DecVal7\",\"DecVal8\",\"DecVal9\",\"DecVal10\"],\"columns\":[]},\"GenericCheckpoints_qCategory4_c204\":{\"help-on\":\"1\",\"helptext\":\"Στο πεδίο \\\"1\\tΠεριγραφή της προτεινόμενης επένδυσης - Περγραφή φυσικού αντικειμένου\\\"  θα πρέπει να περιλαμβάνονται - κατ΄ ελάχιστον - τα ακόλουθα:\\n·\\tΔραστηριότητα της επιχείρησης - νομική μορφή\\n·\\tΣκοπός του Επενδυτικού Σχεδίου - Παραγόμενες Υπηρεσίες\\n·\\tΠλεονεκτήματα της επιχείρησης έναντι των άλλων επιχειρήσεων της περιοχής\\n·\\tΠροϋπολογισμός , κατηγορίες και τεκμηρίωση δαπανών, ρεαλιστικότητα προϋπολογισμού, χρηματοδοτικό σχήμα επενδυτικού σχεδίου\\n·\\tΧρονοδιάγραμμα υλοποίησης της επένδυσης με αναφορά στην απαίτηση για έκδοση αδειών (π.χ. δόμησης) και εκτίμηση του χρόνου για την έκδοσή τους. Στην περίπτωση που απαιτούνται άδειες για την έναρξη της επένδυσης (π.χ. άδεια δόμησης) :\\nα)\\tαναφέρονται οι άδειες\\nβ)\\tπεριγράφεται η διαδικασία αδειοδότησης\\nγ)\\tεκτιμάται ο χρόνος για την έκδοσή τους\\nΑν δεν απαιτείται η έκδοση αδειών ή αυτές έχουν εκδοθεί, παρατίθεται σχετική τεκμηρίωση.\",\"hiddenColumns\":[\"GenericCheckpointsID\",\"RelatedEntityType\",\"RelatedEntityID\",\"CpCode2\",\"CpCode3\",\"CpCode4\",\"CpCode5\",\"CpCode6\",\"CpCode7\",\"CpCode8\",\"CpCode9\",\"CpCode10\",\"IntVal1\",\"IntVal2\",\"IntVal3\",\"IntVal4\",\"IntVal5\",\"IntVal6\",\"IntVal7\",\"IntVal8\",\"IntVal9\",\"IntVal10\",\"IntVal11\",\"IntVal12\",\"IntVal13\",\"Comments12\",\"Comments13\",\"DateVal1\",\"DateVal2\",\"DateVal3\",\"DateVal4\",\"DateVal5\",\"DateVal6\",\"DateVal7\",\"DateVal8\",\"DateVal9\",\"DateVal10\",\"DecVal2\",\"DecVal3\",\"DecVal4\",\"DecVal5\",\"DecVal6\",\"DecVal7\",\"DecVal8\",\"DecVal9\",\"DecVal10\"],\"columns\":[{\"view\":\"\",\"edit\":\"\",\"name\":\"IntVal3\"},{\"view\":\"1\",\"edit\":\"1\",\"vord\":\"200\",\"name\":\"DecVal1\",\"label\":\"11\\t Δημιουργία νέων θέσεων απασχόλησης - Καταγραφή αριθμού των νέων θέσεων απασχόλησης οι οποίες θα δημιουργηθούν. \\nΟι θέσεις απασχόλησης είναι εξαρτημένης εργασίας και υπολογίζονται σε Ετήσιες Μονάδες Εργασίας- ΕΜΕ (Μη αξιολογούμενο κριτήριο)\"},{\"view\":\"1\",\"edit\":\"1\",\"label\":\"1\\tΠεριγραφή της προτεινόμενης επένδυσης - Περιγραφή φυσικού αντικειμένου (Αξιολογούμενο κριτήριο)\",\"vord\":\"30\",\"lcolw\":\"2\",\"colw\":\"10\",\"etype\":\"textarea\",\"required\":\"1\",\"name\":\"Comments1\",\"maxlength\":\"\"},{\"view\":\"1\",\"edit\":\"1\",\"label\":\"2\\tΕπικοινωνιακή περιγραφή της επένδυσης -  Σύντομη περιγραφή (Μη αξιολογούμενο κριτήριο)\",\"vord\":\"40\",\"lcolw\":\"2\",\"colw\":\"10\",\"etype\":\"textarea\",\"required\":\"1\",\"name\":\"Comments2\"},{\"view\":\"1\",\"edit\":\"1\",\"label\":\"3\\tΜεθοδολογία υλοποίησης έργου (Μη αξιολογούμενο κριτήριο)\",\"vord\":\"50\",\"lcolw\":\"2\",\"colw\":\"10\",\"etype\":\"textarea\",\"required\":\"1\",\"name\":\"Comments3\"},{\"view\":\"1\",\"edit\":\"1\",\"label\":\"4\\tΑναμενόμενα αποτελέσματα (Μη αξιολογούμενο κριτήριο)\",\"vord\":\"60\",\"lcolw\":\"2\",\"colw\":\"10\",\"etype\":\"textarea\",\"required\":\"1\",\"name\":\"Comments4\"},{\"view\":\"1\",\"edit\":\"1\",\"label\":\"5\\tΣτόχοι της επένδυσης (Μη αξιολογούμενο κριτήριο)\",\"vord\":\"70\",\"lcolw\":\"2\",\"colw\":\"10\",\"etype\":\"textarea\",\"required\":\"1\",\"name\":\"Comments5\"},{\"view\":\"1\",\"edit\":\"1\",\"label\":\"6\\tΔραστηριότητες επικοινωνίας και δημοσιότητας της επένδυσης (Μη αξιολογούμενο κριτήριο)\",\"vord\":\"80\",\"lcolw\":\"2\",\"colw\":\"10\",\"etype\":\"textarea\",\"required\":\"1\",\"name\":\"Comments6\"},{\"view\":\"1\",\"edit\":\"1\",\"label\":\"7\\tΚρισιμότητα επένδυσης (Μη αξιολογούμενο κριτήριο)\",\"vord\":\"90\",\"lcolw\":\"2\",\"colw\":\"10\",\"etype\":\"textarea\",\"required\":\"1\",\"name\":\"Comments7\"},{\"view\":\"1\",\"edit\":\"1\",\"label\":\"8\\tΠροστιθέμενη αξία επένδυσης (Μη αξιολογούμενο κριτήριο)\",\"vord\":\"100\",\"lcolw\":\"2\",\"colw\":\"10\",\"etype\":\"textarea\",\"required\":\"1\",\"name\":\"Comments8\"},{\"view\":\"1\",\"edit\":\"1\",\"label\":\"9\\tΤρόποι επίτευξης στόχων επένδυσης (Μη αξιολογούμενο κριτήριο)\",\"vord\":\"110\",\"lcolw\":\"2\",\"colw\":\"10\",\"etype\":\"textarea\",\"required\":\"1\",\"name\":\"Comments9\"},{\"view\":\"1\",\"edit\":\"1\",\"label\":\"10\\tΑναμενόμενα οφέλη απο την επένδυση (Μη αξιολογούμενο κριτήριο)\",\"vord\":\"120\",\"lcolw\":\"2\",\"colw\":\"10\",\"etype\":\"textarea\",\"required\":\"1\",\"name\":\"Comments10\"},{\"view\":\"\",\"edit\":\"\",\"label\":\"11\\tΔημιουργία νέων θέσεων απασχόλησης (Μη αξιολογούμενο κριτήριο)\",\"vord\":\"130\",\"lcolw\":\"2\",\"colw\":\"10\",\"etype\":\"textarea\",\"required\":\"\",\"name\":\"Comments11\"}]},\"GenericCheckpoints_qCategory63_c204\":{\"helptext\":\"Για την κατηγορία Β είναι απαραίτητη η συμπλήρωση των στοιχείων της άδειας δόμησης που διαθέτει η επιχείρηση για το τουριστικό κατάλυμα που θα επενδύσει.\",\"hiddenColumns\":[\"GenericCheckpointsID\",\"RelatedEntityType\",\"RelatedEntityID\",\"CpCode1\",\"CpCode2\",\"CpCode3\",\"CpCode4\",\"CpCode5\",\"CpCode6\",\"CpCode7\",\"CpCode8\",\"CpCode9\",\"CpCode10\",\"IntVal3\",\"IntVal4\",\"IntVal5\",\"IntVal6\",\"IntVal7\",\"IntVal8\",\"IntVal9\",\"IntVal10\",\"IntVal11\",\"IntVal12\",\"IntVal13\",\"Comments2\",\"Comments3\",\"Comments4\",\"Comments5\",\"Comments6\",\"Comments7\",\"Comments8\",\"Comments9\",\"Comments10\",\"Comments11\",\"Comments12\",\"Comments13\",\"DateVal1\",\"DateVal2\",\"DateVal3\",\"DateVal4\",\"DateVal5\",\"DateVal6\",\"DateVal7\",\"DateVal8\",\"DateVal9\",\"DateVal10\",\"DecVal1\",\"DecVal2\",\"DecVal3\",\"DecVal4\",\"DecVal5\",\"DecVal6\",\"DecVal7\",\"DecVal8\",\"DecVal9\",\"DecVal10\"],\"columns\":[{\"view\":\"\",\"edit\":\"\",\"name\":\"Comments2\"},{\"view\":\"\",\"edit\":\"\",\"name\":\"Comments3\"},{\"view\":\"\",\"edit\":\"\",\"name\":\"DateVal1\"},{\"view\":\"\",\"edit\":\"\",\"name\":\"DateVal2\"},{\"view\":\"\",\"edit\":\"\",\"name\":\"DateVal3\"}]},\"GenericCheckpoints_qCategory64_c204\":{\"single\":\"1\",\"display\":\"view\",\"detail\":\"1\",\"hiddenColumns\":[\"GenericCheckpointsID\",\"RelatedEntityType\",\"RelatedEntityID\",\"CpCode1\",\"CpCode2\",\"CpCode3\",\"CpCode4\",\"CpCode5\",\"CpCode6\",\"CpCode7\",\"CpCode8\",\"CpCode9\",\"CpCode10\",\"IntVal3\",\"IntVal4\",\"IntVal5\",\"IntVal6\",\"IntVal7\",\"IntVal8\",\"IntVal9\",\"IntVal10\",\"IntVal11\",\"IntVal12\",\"IntVal13\",\"Comments6\",\"Comments7\",\"Comments8\",\"Comments9\",\"Comments10\",\"Comments11\",\"Comments12\",\"Comments13\",\"DateVal1\",\"DateVal2\",\"DateVal3\",\"DateVal4\",\"DateVal5\",\"DateVal6\",\"DateVal7\",\"DateVal8\",\"DateVal9\",\"DateVal10\",\"DecVal1\",\"DecVal2\",\"DecVal3\",\"DecVal4\",\"DecVal5\",\"DecVal6\",\"DecVal7\",\"DecVal8\",\"DecVal9\",\"DecVal10\"],\"columns\":[{\"view\":\"1\",\"edit\":\"1\",\"name\":\"IntVal1\",\"label\":\"1. Πρόβλεψη πρόσληψης νέου προσωπικού για τουλάχιστον 0,2 ΕΜΕ μισθωτής εργασίας (Χρειάζεται για τον υπολογισμό της προσαύξησης της έντασης ενίσχυσης)\",\"etype\":\"select\",\"vord\":\"1\",\"required\":\"1\",\"items\":[{\"val\":\"1\",\"lab\":\"ΝΑΙ\"},{\"val\":\"0\",\"lab\":\"ΟΧΙ\"}]},{\"view\":\"1\",\"edit\":\"1\",\"name\":\"Comments1\",\"label\":\"2. Παρατηρήσεις σχετικά με την πρόσληψη νέου προσωπικού για τουλάχιστον 0,2 ΕΜΕ μισθωτής εργασίας - (Το πεδίο είναι υποχρεωτικό να συμπληρωθεί σε περίπτωση που η απάντηση στο πεδίο 1 είναι ΝΑΙ)\",\"etype\":\"textarea\",\"vord\":\"2\"},{\"view\":\"1\",\"edit\":\"1\",\"name\":\"IntVal2\",\"label\":\"3. Αποδεικτικά στοιχεία εξασφάλισης της Ιδιωτικής Συμμετοχής σε ποσοστό τουλάχιστον του 60% του προτεινόμενου προϋπολογισμού του Επενδυτικού Σχεδίου (Αξιολογούμενο πεδίο)\",\"etype\":\"select\",\"vord\":\"3\",\"required\":\"1\",\"items\":[{\"val\":\"1\",\"lab\":\"ΝΑΙ\"},{\"val\":\"0\",\"lab\":\"ΟΧΙ\"}]},{\"vord\":\"4\",\"view\":\"1\",\"edit\":\"1\",\"name\":\"Comments2\",\"lcolw\":\"4\",\"colw\":\"8\",\"label\":\"4. Τεκμηριώστε τις παραδοχές σχετικά με τις προβλέψεις εσόδων - εξόδων (στοιχεία βιωσιμότητας επιχείρησης) που αφορούν στα πέντε έτη μετά την υλοποίηση του επιχειρηματικού σχεδίου (Αξιολογούμενο πεδίο)\",\"etype\":\"textarea\",\"required\":\"1\"},{\"vord\":\"5\",\"view\":\"1\",\"edit\":\"1\",\"name\":\"Comments3\",\"lcolw\":\"4\",\"colw\":\"8\",\"label\":\"5. Έσοδα - Συμπληρώστε ανά έτος το ποσό του κύκλου εργασιών (Αξιολογούμενο πεδίο)\",\"etype\":\"textarea\",\"required\":\"1\"},{\"vord\":\"6\",\"view\":\"1\",\"edit\":\"1\",\"name\":\"Comments4\",\"lcolw\":\"4\",\"colw\":\"8\",\"label\":\"6. Έξοδα - Συμπληρώστε ανά έτος το ποσό που αφορά σε: \\n1) Κόστος Αγοράς Εξοπλισμού\\n2) Κόστος Μισθοδοσίας\\n3) Λειτουργικές Δαπάνες (ενδεικτικά)\\n4) Μισθώματα – ενοίκια\\n5) Δαπάνες ηλεκτρισμού\\n6) Αναλώσιμα\\n7) Έξοδα Διοίκησης\\n8) Έξοδα Συντήρησης\\n9) Αμοιβές Προσωπικού\\n10) Αμοιβές Τρίτων\\n11) Γενικά Έξοδα\\n12) Έξοδα Προβολής\\n13) Άλλα έξοδα\\n14) Σύνολο Εξόδων (Αξιολογούμενο πεδίο)\",\"etype\":\"textarea\",\"required\":\"1\"},{\"vord\":\"7\",\"view\":\"1\",\"edit\":\"1\",\"name\":\"Comments5\",\"label\":\"7. Κέρδη - Συμπληρώστε ανά έτος το ποσό των κερδών προ αποσβέσεων και φόρων (Αξιολογούμενο πεδίο)\",\"lcolw\":\"4\",\"colw\":\"8\",\"etype\":\"textarea\",\"required\":\"1\"}]},\"GenericCheckpoints_qCategory81_c204\":{\"help-on\":\"1\",\"helptext\":\"Προσοχή : Καθώς με την υποβολή της αίτησης δεν απαιτείται η προσκόμιση προσφορών / προτιμολογίων εφιστούμε την προσοχή στην συμπλήρωση των σχετικών πεδίων η οποία πρέπει να είναι σαφής, αναλυτική και με σχετική τεκμηρίωση όσον αφορά τα επιμέρους κόστη των επιλέξιμων κατηγοριών δαπανών.\",\"hiddenColumns\":[\"GenericCheckpointsID\",\"RelatedEntityType\",\"RelatedEntityID\",\"CpCode1\",\"CpCode2\",\"CpCode3\",\"CpCode4\",\"CpCode5\",\"CpCode6\",\"CpCode7\",\"CpCode8\",\"CpCode9\",\"CpCode10\",\"IntVal2\",\"IntVal3\",\"IntVal4\",\"IntVal5\",\"IntVal6\",\"IntVal7\",\"IntVal8\",\"IntVal9\",\"IntVal10\",\"IntVal11\",\"IntVal12\",\"IntVal13\",\"Comments2\",\"Comments3\",\"Comments4\",\"Comments5\",\"Comments6\",\"Comments7\",\"Comments8\",\"Comments9\",\"Comments10\",\"Comments11\",\"Comments12\",\"DateVal1\",\"DateVal2\",\"DateVal3\",\"DateVal4\",\"DateVal5\",\"DateVal6\",\"DateVal7\",\"DateVal8\",\"DateVal9\",\"DateVal10\",\"DecVal6\",\"DecVal7\",\"DecVal8\",\"DecVal9\",\"DecVal10\"],\"columns\":[{\"name\":\"DecVal5\",\"readonly\":\"1\",\"value\":\"0\"}]},\"GenericCheckpoints_qCategory65_c204\":{\"help-on\":\"1\",\"helptext\":\"Αποδεικτικά στοιχεία εξασφάλισης της Ιδιωτικής Συμμετοχής σε ποσοστό τουλάχιστον του 60% του προτεινόμενου προϋπολογισμού του Επενδυτικού Σχεδίου (εφόσον είναι παραπάνω από ένα, προστίθεται γραμμή)\",\"hiddenColumns\":[\"GenericCheckpointsID\",\"RelatedEntityType\",\"RelatedEntityID\",\"CpCode1\",\"CpCode2\",\"CpCode3\",\"CpCode4\",\"CpCode5\",\"CpCode6\",\"CpCode7\",\"CpCode8\",\"CpCode9\",\"CpCode10\",\"IntVal5\",\"IntVal6\",\"IntVal7\",\"IntVal8\",\"IntVal9\",\"IntVal10\",\"IntVal11\",\"IntVal12\",\"IntVal13\",\"Comments2\",\"Comments3\",\"Comments4\",\"Comments5\",\"Comments6\",\"Comments7\",\"Comments8\",\"Comments9\",\"Comments10\",\"Comments11\",\"Comments12\",\"Comments13\",\"DateVal1\",\"DateVal2\",\"DateVal3\",\"DateVal4\",\"DateVal5\",\"DateVal6\",\"DateVal7\",\"DateVal8\",\"DateVal9\",\"DateVal10\",\"DecVal1\",\"DecVal2\",\"DecVal3\",\"DecVal4\",\"DecVal5\",\"DecVal6\",\"DecVal7\",\"DecVal8\",\"DecVal9\",\"DecVal10\"],\"columns\":[]},\"LinkedEnterprises_qMulti_c204\":{\"columns\":[{\"name\":\"Period\",\"etype\":\"select\",\"items\":[{\"val\":\"2015\",\"lab\":\"2015\"},{\"val\":\"2016\",\"lab\":\"2016\"},{\"val\":\"2017\",\"lab\":\"2017\"},{\"val\":\"2018\",\"lab\":\"2018\"}]}]},\"GenericCheckpoints_qCategory66_c204\":{\"hidden\":\"1\"},\"GenericCheckpoints_qCategory82_c204\":{\"hiddenColumns\":[\"GenericCheckpointsID\",\"RelatedEntityType\",\"CpCode1\",\"CpCode2\",\"CpCode3\",\"CpCode4\",\"CpCode5\",\"CpCode6\",\"CpCode7\",\"CpCode8\",\"CpCode9\",\"CpCode10\",\"IntVal1\",\"IntVal2\",\"IntVal3\",\"IntVal4\",\"IntVal5\",\"IntVal6\",\"IntVal7\",\"IntVal8\",\"IntVal9\",\"IntVal10\",\"IntVal11\",\"IntVal12\",\"IntVal13\",\"Comments8\",\"Comments9\",\"Comments10\",\"Comments11\",\"Comments12\",\"Comments13\",\"DateVal1\",\"DateVal2\",\"DateVal3\",\"DateVal4\",\"DateVal5\",\"DateVal6\",\"DateVal7\",\"DateVal8\",\"DateVal9\",\"DateVal10\",\"DecVal8\",\"DecVal9\",\"DecVal10\"],\"columns\":[{\"view\":\"\",\"edit\":\"\",\"name\":\"RelatedEntityID\",\"required\":\"\"}]},\"GenericCheckpoints_qCategory91_c204\":{\"hiddenColumns\":[\"GenericCheckpointsID\",\"RelatedEntityType\",\"RelatedEntityID\",\"CpCode1\",\"CpCode2\",\"CpCode3\",\"CpCode4\",\"CpCode5\",\"CpCode6\",\"CpCode7\",\"CpCode8\",\"CpCode9\",\"CpCode10\",\"IntVal2\",\"IntVal3\",\"IntVal4\",\"IntVal5\",\"IntVal6\",\"IntVal7\",\"IntVal8\",\"IntVal9\",\"IntVal10\",\"IntVal11\",\"IntVal12\",\"IntVal13\",\"Comments1\",\"Comments2\",\"Comments3\",\"Comments4\",\"Comments5\",\"Comments6\",\"Comments7\",\"Comments8\",\"Comments9\",\"Comments10\",\"Comments11\",\"Comments12\",\"Comments13\",\"DateVal1\",\"DateVal2\",\"DateVal3\",\"DateVal4\",\"DateVal5\",\"DateVal6\",\"DateVal7\",\"DateVal8\",\"DateVal9\",\"DateVal10\",\"DecVal1\",\"DecVal2\",\"DecVal3\",\"DecVal4\",\"DecVal5\",\"DecVal6\",\"DecVal7\",\"DecVal8\",\"DecVal9\",\"DecVal10\"],\"columns\":[]}}"
}