{
  "type": "object",
  "properties": {
    "tab1": {
      "type": "object",
      "title": "Γενικά Στοιχεία Πρόσκλησης",
      "properties": {
        "TITLOS_PROSKLHSHS": {
          "type": "string",
          "title": "Τίτλος Πρόσκλησης"
        },
        "KODIKOS_PROSKLHSHS": {
          "type": "string",
          "title": "Κωδικός Πρόσκλησης ΟΠΣ"
        },
        "AA_PROSKLHSHS": {
          "type": "number",
          "title": "Α/Α ΟΠΣ"
        },
	    "ANALYTIS": {
          "type": "string",
          "title": "Αναλυτής"
        },
        "EKDOSI_PROSKLHSHS": {
          "type": "number",
          "title": "Έκδοση"
        },
        "KODIKOS_FOREA_EGKRISHS": {
          "type": "string",
          "title": "Φορέας Πρόσκλησης"
        },
        "ID_XEIRISTHS_PRAXHS_USERNAME": {
          "type": "string",
          "title": "Αρμόδιος Επικοινωνίας Πρόσκλησης"
        },
        "ARITHMOS_FEK": {
          "type": "string",
          "title": "Αριθμός Πρωτοκόλλου / ΦΕΚ Πρόσκλησης"
        },
        "ADA": {
          "type": "string",
          "title": "ΑΔΑ"
        },
        "DATE_ENARKSHS_ISXYOS": {
          "type": "string",
          "title": "Ημερομηνία Έναρξης Ισχύος"
        },
        "DIARKEIA_ISXYOS": {
          "type": "number",
          "title": "Διάρκεια Ισχύος (Σε Μήνες)"
        },
		"FLAG_DAPANES_PRIN_YPOVOLI": {
              "type": "string",
              "title": "Απαγορεύεται η Υποβολή Δαπανών Πριν την Hμερομηνία Υποβολής του Επενδυτικού Σχεδίου",
              "enum": [
                "0",
                "1"
              ]
        },
		"DATE_ENARKSHS_EPILEKSIMOTITAS_DAPANON": {
          "type": "string",
          "title": "Ημερομηνία Έναρξης Επιλεξιμότητας Δαπανών"
        },
		"implementationStartDateChoice": {
          "type": "string",
          "title": "Ημερομηνία Έναρξης Υλοποίησης της Πράξης για την Βεβαίωση Ολοκλήρωσης θεωρείται",
          "enum": [
               "1",
               "2"
             ]
        },
        "EIDOS_AJIOLOGHSHS": {
          "type": "string",
          "title": "Είδος Αξιολόγησης"
        },
		"MEGISTOS_ARITHMOS_ENDIAMESON": {
          "type": "number",
          "title": "Μέγιστος Αριθμός Ενδιάμεσων Αιτημάτων Ελέγχου",
		  "maximum": 9
        },
		"MEGISTOS_ARITHMOS_ENDIAMESON_EXTRA": {
			"type": "string",
			"title": "Τα Απορριφθέντα Αιτήματα Ελέγχου λαμβάνοται υπ' όψιν στον Μέγιστο Αριθμό Ενδιάμεσων Αιτημάτων Ελέγχου",
			"enum": [
                "0",
                "1"
              ]
		},
        "AR_KOINOP": {
          "type": "string",
          "title": "Αρ. Kοινοποίησης / Γνωστοποίησης"
        },
        "AR_APOF_EE": {
          "type": "string",
          "title": "Αρ. Απόφασης Έγκρισης ΕΕ"
        },
				"AUTOMATIC_SEND_DDD": {
			"type": "string",
			"title": "Αυτόματη Αποστολή Δελτίων Δήλωσης Δαπανών",
			"enum": [
                "0",
                "1"
              ]
		},
		"FOREAS_PLIROMIS": {
          "type": "string",
          "title": "Φορέας Πληρωμής"
        },	
		"ONOMATEPONYMO_SYNTAKTA": {
          "type": "string",
          "title": "Ονοματεπώνυμο Συντάκτα"
        },
		"KATASTASI_DELTIOY_DILOSIS_DAPANON": {
          "type": "string",
          "title": "Κατάσταση Δελτίου Δήλωσης Δαπανών",
          "enum": [
               "302",
               "304"
             ]
        },		

        "title1": {
            "title": "Εξώφυλλο εκτυπωτικών γραμμή 1"
        },
        "title2": {
            "title": "Εξώφυλλο εκτυπωτικών γραμμή 2"
        },
        "title3": {
            "title": "Εξώφυλλο εκτυπωτικών γραμμή 3"
        },
        "headerLogo": {
            "title": "Αρχείο Λογότυπου Επικεφαλίδας"
        },
		"genericCheckpointCategoryOfCompletionDate": {
            "title": "ID κατηγορίας checkpoint που περιέχει τη στήλη στην οποία καταχωρείται η Ημερομηνία Ολοκλήρωσης"
        },
		"columnOfCompletionDate": {
            "title": "Ονομασία στήλης στην οποία καταχωρείται η Ημερομηνία Ολοκλήρωσης "
        },		
        "logo": {
            "title": "Αρχείο Λογότυπου Υποσέλιδου"
        },
		
        "uiLanguage": {
            "title": "Γλώσσα Γραφικού Περιβάλλοντος",
            "enum": ["Ελληνικά", "Αγγλικά"]
        },
        "escrowText": {
            "title": "Κείμενο για τη δήλωση προσχώρησης στον escrow"
        },
        "KATHESTOS_ENISXYSHS_LIST": {
          "type": "array",
          "title": "Εφαρμοστέοι Κανονισμοί / Καθεστώτα Ενίσχυσης",
          "items": {
            "type": "object",
            "properties": {
              "KATHESTOS_ENISXYSHS": {
                "type": "string",
                "title": "Εφαρμοστέος Κανονισμός / Καθεστώς Ενίσχυσης"
              }
            }
          }
        }
      }
    },
    "tab2": {
      "type": "array",
      "default": [
        {}
      ],
      "items": {
        "type": "object",
        "title": "Θεματικοί Στόχοι, Επενδυτικές Προτεραιότητες, Ειδικοί Στόχοι",
        "properties": {
          "ID_ATP": {
            "type": "string",
            "title": " ID_ATP - Κωδικός Άξονας Ταμείο Περιφέρεια"
          },
          "EP_PERIGRAFH": {
            "type": "string",
            "title": "Επιχειρησιακό Πρόγραμμα",
            "enum": [
              "1.",
              "2.",
              "3.",
              "4.",
              "5."
            ]
          },
          "AXONAS_PERIGRAFH": {
            "type": "string",
            "title": "Άξονας Προτεραιότητας"
          },
          "KATHGORIA_PER": {
            "type": "string",
            "title": "Κατηγορία Περιφέρειας"
          },
          "KODIKOS_EKXORISIS": {
            "type": "string",
            "title": "Κωδικός Εκχώρησης"
          },
          "TAMEIO": {
            "type": "string",
            "title": "Ταμείο"
          },
          "THEMATIKOI_STOXOI": {
            "type": "string",
            "title": "Θεματικός Στόχος"
          },
          "EPENDYTIKES_PROTERAIOTHTES": {
            "type": "string",
            "title": "Επενδυτική Προτεραιότητα"
          },
          "EIDIKOI_STOXOI": {
            "type": "string",
            "title": "Ειδικός Στόχος"
          }
        }
      }
    },
    "tab3": {
      "type": "array",
      "default": [
        {}
      ],
      "items": {
        "type": "object",
        "title": "Προβλεπόμενος Δείκτης Παρακολούθησης",
        "properties": {
          "EIDOS_DEIKTH": {
            "type": "string",
            "title": "Είδος Δείκτη"
          },
          "ONOMASIA_DEIKTH": {
            "type": "string",
            "title": "Ονομασία Δείκτη"
          },
          "MONADA_METRHSHS": {
            "type": "string",
            "title": "Μονάδα Μέτρησης"
          }
        }
      }
    },
    "tab4": {
      "type": "object",
      "properties": {
        "INVITATION_ABOUT": {
          "type": "object",
          "title": "Η πρόσκληση αφορά",
          "properties": {
            "CCI_KOINO_SXEDIO_DRASHS": {
              "type": "string",
              "title": "Πράξεις που εντάσσονται σε κοινό σχέδιο δράσης",
              "enum": [
                "0",
                "1"
              ]
            },
            "XRHMATOD_PAN_FLAG": {
              "type": "string",
              "title": "Πράξεις που περιλαμβάνουν χρηματοδότηση ΠΑΝ",
              "enum": [
                "0",
                "1"
              ]
            },
            "ENISXYSH_MME": {
              "type": "string",
              "title": "Ενίσχυση ΜΜΕ",
              "enum": [
                "0",
                "1"
              ]
            },
            "KOIN_KAIN_DIAKR_SYN": {
              "type": "string",
              "title": "Κοινωνική Καινοτομία ή Διακρατική Συνεργασία ή και τα δύο",
              "enum": [
                "0",
                "1",
                "2",
                "3"
              ]
            },
            "MICRODATA": {
              "type": "string",
              "title": "Συλλογή, επεξεργασία, αποθήκευση, διαβίβαση μίκροδεδομενων",
              "enum": [
                "0",
                "1"
              ]
            }
          }
        },
        "CODED_DATA_FOR_INVITATION": {
          "type": "object",
          "title": "Κωδικοποιημένα Στοιχεία Πρόσκλησης",
          "properties": {
            "OPSMorfh_Xrhmatodothshs_ID_LIST": {
              "type": "array",
              "title": "Μορφές Χρηματοδότησης",
              "items": {
                "type": "object",
                "properties": {
                  "OPSMorfh_Xrhmatodothshs_ID": {
                    "type": "string",
                    "title": "Μορφή Χρηματοδότησης"
                  }
                }
              }
            },
            "OPSEdafikh_Diastash_Typos_ID_LIST": {
              "type": "array",
              "title": "Τύποι Εδαφικής Μονάδας",
              "items": {
                "type": "object",
                "properties": {
                  "OPSEdafikh_Diastash_Typos_ID": {
                    "type": "string",
                    "title": "Τύποι Εδαφικής Μονάδας"
                  }
                }
              }
            },
            "OPSEdafikh_Diastash_Mhxanismos_id_LIST": {
              "type": "array",
              "title": "Μηχανισμοί Εδαφικής Διάστασης",
              "items": {
                "type": "object",
                "properties": {
                  "OPSEdafikh_Diastash_Mhxanismos_id": {
                    "type": "string",
                    "title": "Μηχανισμός Εδαφικής Διάστασης",
                    "enum": [
                      "1.",
                      "2.",
                      "3.",
                      "4.",
                      "5."
                    ]
                  }
                }
              }
            },
            "OPSDeytereyon_stoxos_EKT_ID_LIST": {
              "type": "array",
              "title": "Δευτερέυοντες θεματικοί στόχοι ΕΚΤ",
              "items": {
                "type": "object",
                "properties": {
                  "OPSDeytereyon_stoxos_EKT_ID": {
                    "type": "string",
                    "title": "Δευτερέυων θεματικός στόχος ΕΚΤ"
                  }
                }
              }
            },
            "OPSOikonomikh_Drasthriothta_id_LIST": {
              "type": "array",
              "title": "Οικονομικές Δραστηριότητες",
              "items": {
                "type": "object",
                "properties": {
                  "OPSOikonomikh_Drasthriothta_id": {
                    "type": "string",
                    "title": "Οικονομική Δραστηριότητα"
                  }
                }
              }
            },
            "ID_GEO_LIST": {
              "type": "array",
              "title": "Γεωγραφικές Θέσεις (Περιφέρειες ή Νομοί/ΟΤΑ) - (NUTS/LAU)",
              "items": {
                "type": "object",
                "properties": {
                  "ID_GEO": {
                    "type": "string",
                    "title": "Γεωγραφική Θέση (Περιφέρεια ή Νομός/ΟΤΑ) - (NUTS/LAU)"
                  }
                }
              }
            }
          }
        }
      }
    },
    "tab5": {
      "type": "object",
      "properties": {
        "PEDIA_PAREMVASHS_OBJ": {
          "type": "object",
          "properties": {
            "PEDIA_PAREMVASHS_LIST": {
              "type": "array",
              "items": {
                "type": "object",
                "properties": {
                  "PEDIA_PAREMVASHS": {
                    "type": "string",
                    "title": "Πεδία Παρέμβασης"
                  },
                  "KATHGORIA_PERIFEREIAS": {
                    "type": "string",
                    "title": "Κατηγορία Περιφέρειας"
                  },
                  "DHMOSIA_DAPANH": {
                    "type": "number",
                    "title": "Δημοσία Δαπάνη"
                  }
                }
              },
              "default": [
                {}
              ]
            },
            "DHMOSIA_DAPANH_TOTAL_OBJ": {
              "type": "object",
              "properties": {
                "DHMOSIA_DAPANH_TOTAL": {
                  "type": "number",
                  "title": "Σύνολο Δημοσίων Δαπανών"
                }
              }
            }
          }
        },
        "INVITATION_TOTAL_AMOUNTS": {
          "type": "object",
          "properties": {
            "IDIOTIKI_SYMMETOXH": {
              "type": "number",
              "title": "Εκτιμώμενη Ιδιωτική Συμμετοχή"
            }
          }
        }
      }
    },
    "tab6": {
      "type": "object",
      "properties": {
        "ENTASI_ENISXISIS_OBJ": {
          "type": "object",
          "properties": {
            "min": {
              "type": "number",
              "title": "Ελάχιστος Επιλέξιμος Προϋπολογισμός ανά Πρόταση €"
            },
            "max": {
              "type": "number",
              "title": "Μέγιστος Επιλέξιμος Προϋπολογισμός ανά Πρόταση €"
            },
            "MAX_ENTASI_ENISXISIS": {
              "type": "number",
              "title": "Μέγιστη Προσαύξηση Έντασης Ενίσχυσης %"
            },			
			"MAX_POSOSTO_KALIPSIS_APO_PROKATAVOLES": {
              "type": "number",
              "title": "Μέγιστo Ποσοστό Κάλυψης Εγκεκριμένης Δημόσιας Δαπάνης από Προκαταβολές %"
            },
			"MAX_POSOSTO_KALIPSIS_APO_PROKATAVOLES_EREUNITIKOI_FOREIS": {
              "type": "number",
              "title": "Μέγιστo Ποσοστό Κάλυψης Εγκεκριμένης Δημόσιας Δαπάνης από Προκαταβολές % (Ερευνητικοί Φορείς)"
            },
			"KODIKOI_EPIXEIRISEON_XORIS_EGGIITIKES": {
              "type": "string",
              "title": "Κωδικοί Δικαιούχων που δεν υποχρεούνται να καταθέσουν εγγγυητικές επιστολές (comma seperated)"
            },
			"MIN_POSOSTO_YLOPOIISIS_GIA_AITIMA_ELEGXOU": {
              "type": "number",
              "title": "Ελάχιστο Ποσοστό Υλοποίησης Επιχορηγούμενου Π/Υ για Αίτημα Ενδιάμεσου Ελέγχου %"
            },
			"MAX_POSOSTO_YLOPOIISIS_GIA_AITIMA_ELEGXOU": {
              "type": "number",
              "title": "Μέγιστo Ποσοστό Υλοποίησης Επιχορηγούμενου Π/Υ για Αίτημα Ενδιάμεσου Ελέγχου %"
            },
			"MAX_POSOSTO_YLOPOIISIS_GIA_AITIMA_ELEGXOU_EREUNITIKOI_FOREIS": {
              "type": "number",
              "title": "Μέγιστo Ποσοστό Υλοποίησης Επιχορηγούμενου Π/Υ για Αίτημα Ενδιάμεσου Ελέγχου % (Ερευνητικοί Φορείς)"
            },
			"ARSH_ELEGXOU_ORTHOTITAS_GIA_DIMOSIA_DAPANI": {
			  "type": "string",
			  "default": "0",
              "title": "Άρση ελέγχου ορθότητας σχετικά με την υπέρβαση της δημόσιας δαπάνης (LEADER)"
            }
          }
        },
        "KATHGORIES_DAPANON_OBJ": {
          "type": "object",
          "properties": {
            "groups": {
              "type": "array",
              "items": {
                "type": "object",
                "properties": {
                  "id": {
                    "title": "Group"
                  },
                  "ANOTERO_POSO": {
                    "type": "number",
                    "title": "Ανώτερο ποσό"
                  },
                  "ELAXISTO_POSO": {
                    "type": "number",
                    "title": "Ελάχιστο ποσό"
                  },
                  "ANOTERO_POSOSTO_EPI_TOY_PROIPOLOGISMOY": {
                    "type": "number",
                    "title": "Μέγιστο ποσοστό επί του προυπολογισμού",
                    "minimum": 0,
                    "maximum": 100
                  },
                  "ELAXISTO_POSOSTO_EPI_TOY_PROIPOLOGISMOY": {
                    "type": "number",
                    "title": "Ελάχιστο ποσοστό επί του προυπολογισμού",
                    "minimum": 0,
                    "maximum": 100
                  }
                }
              }
            },
            "KATHGORIES_DAPANON_LIST": {
              "type": "array",
              "title": "Κατηγορίες Δαπανών",
              "items": {
                "type": "object",
                "properties": {
                  "AA": {
                    "type": "string",
                    "title": "AA",
                    "readonly": false
                  },
                  "title": {
                    "title": "Τίτλος"
                  },
                  "group": {
                    "title": "group"
                  },
                  "KATHGORIA_ENERGEIAS": {
                    "type": "string",
                    "title": "Κατηγορία Ενέργειας",
                    "enum": [
                      "1.",
                      "2.",
                      "3.",
                      "4.",
                      "5."
                    ]
                  },
                  "KATHGORIA_PERIFEREIAS": {
                    "type": "string",
                    "title": "Κατηγορία Περιφέρειας"
                  },
                  "ANOTERO_POSO": {
                    "type": "string",
                    "title": "Ανώτερο ποσό"
                  },
                  "ELAXISTO_POSO": {
                    "type": "string",
                    "title": "Ελάχιστο ποσό"
                  },
                  "ANOTERO_POSOSTO_EPI_TOY_PROIPOLOGISMOY": {
                    "type": "number",
                    "title": "Μέγιστο ποσοστό επί του προυπολογισμού",
                    "minimum": 0,
                    "maximum": 100
                  },
                  "ELAXISTO_POSOSTO_EPI_TOY_PROIPOLOGISMOY": {
                    "type": "number",
                    "title": "Ελάχιστο ποσοστό επί του προυπολογισμού",
                    "minimum": 0,
                    "maximum": 100
                  },
                  "ENTASI_ENISXISIS": {
                    "type": "number",
                    "title": "Ένταση Ενίσχυσης",
                    "minimum": 0,
                    "maximum": 100
                  },
				  "RITRA_EUELIKSIAS": {
				    "type": "string",
					"default": "0",
                    "title": "Ρήτρα Ευελιξίας"
                  }
                }
              },
              "default": [
                {
                  "AA": "1"
                }
              ]
            }
          }
        }
      }
    },
    "tab7": {
      "type": "object",
      "properties": {
        "numberOfLocations": {
          "type": "number",
          "title": "Αριθμός Τόπων Υλοποίησης ανά Φορέα"
        },
        "attachmentInstruction": {
          "title": "Γενικές Οδηγίες για Συνημμένα",
          "type": "string"
        },
		"excludedCnCodes": {
          "title": "Κωδικοί προτάσεων που εξαιρούνται απο το όριο για το συνολικό μέγεθος συνημμένων (comma seperated)",
          "type": "string"
        },
        "limitOfExcludedCnCodes": {
          "type": "number",
          "minimum": 50,
          "maximum": 200,
          "title": "Όριο συνολικού μεγέθους συνημμένων αρχείων για τις προτάσεις που εξαιρούνται απο το γενικό όριο (MB). Οι επιτρεπόμενες τιμές είναι από 50 έως 200(ΜΒ). Αν δεν συμπληρωθεί το πεδίο, το όριο παραμένει στα 50 (ΜΒ)"
        },		
        "attachment": {
          "type": "array",
          "title": "Συνημμένα Έγγραφα",
          "items": {
            "type": "object",
            "properties": {
              "name": {
                "type": "string",
                "title": "Όνομα"
              },
              "description": {
                "type": "string",
                "title": "Περιγραφή"
              },
              "prototype": {
                "type": "string",
                "title": "Πρότυπο (link)"
              },
              "mandatory": {
                "type": "boolean",
                "title": "Υποχρεωτικό"
              }
            }
          }
        }
      }
    },
    "tab8": {
      "type": "object",
      "properties": {
        "onOff": {
          "type": "array",
          "title": "On / Off Κριτήρια",
          "items": {
            "type": "object",
            "properties": {
              "aa": {
                "title": "Α/Α"
              },
              "name": {
                "title": "Κριτήριο"
              },
              "group": {
                "title": "Ομάδα"
              }
            }
          }
        },
        "groupOnOff": {
          "type": "array",
          "title": "Ομάδες Κριτηρίων On / Off",
          "items": {
            "type": "object",
            "properties": {
              "aa": {
                "title": "Α/Α"
              },
              "name": {
                "title": "Ομάδα"
              }
            }
          }
        },
        "critiria": {
          "type": "array",
          "title": "Κριτήρια Αξιολόγησης",
          "items": {
            "type": "object",
            "properties": {
              "aa": {
                "title": "Α/Α"
              },
              "name": {
                "title": "Κριτήριο"
              },
              "weight": {
                "title": "Βάρος",
                "type": "number"
              },
              "group": {
                "title": "Ομάδα"
              }
            }
          }
        },
        "group": {
          "type": "array",
          "title": "Ομάδες Κριτηρίων",
          "items": {
            "type": "object",
            "properties": {
              "aa": {
                "title": "Α/Α"
              },
              "name": {
                "title": "Ομάδα"
              },
              "weight": {
                "title": "Βάρος",
                "type": "number"
              }
            }
          }
        }
      }
    },
    "compiled": {
      "type": "string"
    }
  }
}
